sendcloud/__init__.py
sendcloud/__version__.py
sendcloud/classes/__init__.py
sendcloud/classes/brands.py
sendcloud/classes/integrations_and_orders.py
sendcloud/classes/invoices.py
sendcloud/classes/labels.py
sendcloud/classes/parcels.py
sendcloud/classes/returns.py
sendcloud/classes/sender_address.py
sendcloud/classes/shipping_methods.py
sendcloud/classes/users.py
sendcloud/classes/webhooks.py
sendcloud/http/__init__.py
sendcloud/http/client.py
sendcloud/http/exceptions.py
sendcloud_python-0.1.5.dist-info/LICENSE
sendcloud_python-0.1.5.dist-info/METADATA
sendcloud_python-0.1.5.dist-info/WHEEL
sendcloud_python-0.1.5.dist-info/top_level.txt
sendcloud_python-0.1.5.dist-info/RECORD
