Metadata-Version: 2.2
Name: sendcloud-python
Version: 0.1.5
Home-page: https://github.com/stasfilin/sendcloud
Author: Stanislav Filin
License: MIT
License-File: LICENSE
Requires-Dist: requests>=2.23.0
Provides-Extra: develop
Requires-Dist: requests>=2.23.0; extra == "develop"
Requires-Dist: pytest==7.1.2; extra == "develop"
Requires-Dist: black==24.8.0; extra == "develop"
Requires-Dist: requests-mock==1.8.0; extra == "develop"
Requires-Dist: pytest-mock==3.1.0; extra == "develop"
Dynamic: author
Dynamic: description
Dynamic: description-content-type
Dynamic: home-page
Dynamic: license
Dynamic: provides-extra
Dynamic: requires-dist
